var alminhas={"type":"FeatureCollection","features":[{"type":"Feature","geometry":{"type":"Point","coordinates":[-8.389885,41.145503,0]},"properties":{"name":"Devesa, Rua Central da Devesa","FICHA INVENTÁRIO":"0077-PAR-PT","FREGUESIA":"Sobreira","PAINEL":"Painel de azulejo, policromado.","LAT":41.145503,"LONG":-8.389885,"DESCRIÇÃO DO ORATÓRIO":"Oratório tipo nicho, embutido em construção em tijolo, com topo em ângulo agudo e cobertura em telhas de meia cana, assente sobre um muro. Edícula relevada de topo redondo, rematada por cruz latina relevada, assente sobre parapeito saliente.","TIPOLOGIA":"Nicho","OBS":"https://docs.google.com/document/d/e/2PACX-1vT89hsQxx7wtfkWwhaudb5KXEpYJ30Th41I4JS3U_wXkkFr4k2PQM4gowG1RINAWcNdJU8WDkF1yAuA/pub","gx_media_links":"https://doc-0g-ag-mymaps.googleusercontent.com/untrusted/hostedimage/ir60lo368nej76r22q4cs4hp0c/2o506pr9othp0kr2nj3i0ilhu0/1675197059250/3evDZZ2F1ONbZ8Mo7WuI6QKm2vmYGVzF/00061990690341275947/5AI-xGzw_u7XJ--KVVcsCWYoR4TFu1lgbVVh9thLZYY-aB7QuWPXOGBBCG247rYlVrb_PuQh88pjwv_NxeddrUZo3b59lMAwfhUsBVwKVwOml1gcbr2cgUvKLndK0IjTp1gTjKOaFX9i80rsR84KHnz_J1NmO6ib2w_qIXh9SHLCBw9yfhRUdeTVSZpnSEzYvwSkpE_0?session=0&fife"}},{"type":"Feature","geometry":{"type":"Point","coordinates":[-8.38786,41.14073,0]},"properties":{"name":"Outeiro, Rua do Outeiro","FICHA INVENTÁRIO":"0078-PAR-PT","FREGUESIA":"Sobreira","PAINEL":"Tem painel","LAT":41.14073,"LONG":-8.38786,"DESCRIÇÃO DO ORATÓRIO":"Oratório em granito, tipo estela, embutido a três quartos num muro. Entablamento de topo levemente arredondado, rematado por cruz latina, assente num plinto prismático quadrangular. Edícula retangular de volta redonda, protegida do exterior por gradeamento metálico com motivos circulares em espiral. Abaixo, no embasamento, peto quadrangular com tampo metálico. Monumento assente sobre soco granítico retangular.","TIPOLOGIA":"Nicho","OBS":"https://docs.google.com/document/d/e/2PACX-1vSaNh0Y9kdDkiN18DLvB8H461MwN8mCbCFUUppcz1aTAmeQOoKhEiv-u0Fk6Im4ukJettQwAVoIuRbE/pub","gx_media_links":"https://doc-0s-ag-mymaps.googleusercontent.com/untrusted/hostedimage/ir60lo368nej76r22q4cs4hp0c/i7tvnjf59oj9sf7tma70uee2h0/1675197059250/3evDZZ2F1ONbZ8Mo7WuI6QKm2vmYGVzF/00061990690341275947/5AI-xGzzpNfEF5tAjoI1npKI2g9OuTHGsmk5zllTord8Ml-VmFkRIbUHHZD53TFpDn0Hv8f9sN7aAx-FGcMHN82-wNmoBMkAAn-xFTuIZUZBJjqef5w_vTZw13gehprdj9qgNcnwlKtU5_7qtKIMhkkkr3JwaDuuUW3kX-gwND8Qj-1CNtxOteJd07-6h7Z2rQN5hKzU?session=0&fife"}}]};
