var alminhas={"type": "FeatureCollection","name": "paredes","crs": { "type": "name", "properties": { "name": "urn:ogc:def:crs:OGC:1.3:CRS84" } },"features": [{ "type": "Feature", "properties": { "name": "Devesa, Rua Central da Devesa", "DESCRIÇÃO DO ORATÓRIO": "Oratório tipo nicho, embutido em construção em tijolo, com topo em ângulo agudo e cobertura em telhas de meia cana, assente sobre um muro. Edícula relevada de topo redondo, rematada por cruz latina relevada, assente sobre parapeito saliente.", "FICHA INVENTÁRIO": "0077-PAR-PT", "FREGUESIA": "Sobreira", "LAT": "41.145503", "LONG": "-8.389885", "OBS": "https://docs.google.com/document/d/e/2PACX-1vT89hsQxx7wtfkWwhaudb5KXEpYJ30Th41I4JS3U_wXkkFr4k2PQM4gowG1RINAWcNdJU8WDkF1yAuA/pub", "PAINEL": "Painel de azulejo, policromado.", "TIPOLOGIA": "Nicho", "gx_media_links": "https://doc-00-58-mymaps.googleusercontent.com/untrusted/hostedimage/ohe0dbgcv9jn7mbp3tk1ghb69o/65s3rev53rhqob8okkun5rhqr0/1692390680500/3evDZZ2F1ONbZ8Mo7WuI6QKm2vmYGVzF/07330417508546578562/5ACnmet7UNa7ILlyOzvX7ut3qj8NV7E9RcA86ImdTJpw8VfDoi1oDud0TxIywuEjiYQf2aVhhT_GwNUpUol82OTbaPJREQ2SoW7MCmu8bXUozGE0Ja76TjQOYDG9BLeCHu1OnWWZYMOvknn5DfU3s0_-Nflu_2dISoHps_9bmI5QSK29gEldeOeViNCeni3G8s6qzCJ4?session=0&fife" }, "geometry": { "type": "Point", "coordinates": [ -8.389885, 41.145503, 0.0 ] } },{ "type": "Feature", "properties": { "name": "Outeiro, Rua do Outeiro", "DESCRIÇÃO DO ORATÓRIO": "Oratório em granito, tipo estela, embutido a três quartos num muro. Entablamento de topo levemente arredondado, rematado por cruz latina, assente num plinto prismático quadrangular. Edícula retangular de volta redonda, protegida do exterior por gradeamento metálico com motivos circulares em espiral. Abaixo, no embasamento, peto quadrangular com tampo metálico. Monumento assente sobre soco granítico retangular.", "FICHA INVENTÁRIO": "0078-PAR-PT", "FREGUESIA": "Sobreira", "LAT": "41.14073", "LONG": "-8.38786", "OBS": "https://docs.google.com/document/d/e/2PACX-1vSaNh0Y9kdDkiN18DLvB8H461MwN8mCbCFUUppcz1aTAmeQOoKhEiv-u0Fk6Im4ukJettQwAVoIuRbE/pub", "PAINEL": "Tem painel", "TIPOLOGIA": "Nicho", "gx_media_links": "https://doc-0k-58-mymaps.googleusercontent.com/untrusted/hostedimage/ohe0dbgcv9jn7mbp3tk1ghb69o/sae7ds8qt3h3oueli11en17mv4/1692390680500/3evDZZ2F1ONbZ8Mo7WuI6QKm2vmYGVzF/07330417508546578562/5ACnmet7YL4a-59_aXUxxyZ5Oi1pV59NkJT-KBGwh-N9vCCValvzFXn5Xu196jRtpep_p7zURO9wX-R3ML5NbGzgWQrI1egGVvGOEvFV6CDFOF_e9VY_64fYTgvw3KrPQ-Rmwor7cra2Ei9dBxrFvHT3jJB8g57tbIe1JswQbF93SEJB1ia6V4PB-KTuOKy9Xm8s9MWQ?session=0&fife" }, "geometry": { "type": "Point", "coordinates": [ -8.38786, 41.14073, 0.0 ] } },{ "type": "Feature", "properties": { "name": "Santa Comba, Largo das Alminhas", "DESCRIÇÃO DO ORATÓRIO": "Oratório em granito, tipo nicho, de secção paralelepipédica, onde se encontra embutido um nicho em granito, de vão retangular e topo arredondado, rematado por uma cruz relevada. Protege do exterior um gradeamento metálico, ornado com enrolamentos. Abaixo, um peto com tampo metálico.", "FICHA INVENTÁRIO": "0389-PAR-PT", "FREGUESIA": "Sobreira", "LAT": "41.113175", "LONG": "-8.399404", "OBS": "https://docs.google.com/document/d/e/2PACX-1vSe6-9ryjiFxMj3vsh7OBJMCTzd0DVJk2kMngtEeEBg4AADiv09s_A7N-IL0cQiJvu8mJqRLXSk0Z4T/pub", "PAINEL": "Painel em azulejo policromado.", "TIPOLOGIA": "Nicho", "gx_media_links": "https://doc-14-58-mymaps.googleusercontent.com/untrusted/hostedimage/ohe0dbgcv9jn7mbp3tk1ghb69o/tr2rmvgiapcav7c9bl6pp5qd1c/1692390680500/3evDZZ2F1ONbZ8Mo7WuI6QKm2vmYGVzF/07330417508546578562/5ACnmet6yqKBS8X-id0VLG5mNSzz_Z1_kUWsF1GxJ6vEf4Lk2T7ZUXtii8uupyA2DeM6kREeFvbhTVBbKEowhum61P-19hqVSbPU2Zh3_EqQowVERYKETmEH9lUgVgHBuHuf4V3f5gmasIIytq2_-O-ef0gKH6ztGkR6bLDrP7C6FqizKbyah85AMHIRcJee_KyenjEh6Y-H4hAyKepNLBcpDtu85xDZL1CSR8EFhJNpcqcIUKXJkGA?session=0&fife" }, "geometry": { "type": "Point", "coordinates": [ -8.399404, 41.113175, 0.0 ] } }]};
